{"v":"5.7.1","fr":60,"ip":0,"op":392,"w":500,"h":500,"nm":"Bird","ddd":0,"assets":[{"id":"comp_0","layers":[{"ddd":0,"ind":1,"ty":4,"nm":"Ellipse 4","sr":1,"ks":{"o":{"a":0,"k":100,"ix":11},"r":{"a":0,"k":40,"ix":10},"p":{"a":0,"k":[268.054,98.568,0],"ix":2},"a":{"a":0,"k":[0,0,0],"ix":1},"s":{"a":0,"k":[100,100,100],"ix":6}},"ao":0,"shapes":[{"ty":"gr","it":[{"d":1,"ty":"el","s":{"a":0,"k":[5.496,5.496],"ix":2},"p":{"a":0,"k":[0,0],"ix":3},"nm":"Ellipse Path 1","mn":"ADBE Vector Shape - Ellipse","hd":false},{"ty":"fl","c":{"a":0,"k":[1,1,1,1],"ix":4},"o":{"a":0,"k":100,"ix":5},"r":1,"bm":0,"nm":"Fill 1","mn":"ADBE Vector Graphic - Fill","hd":false},{"ty":"tr","p":{"a":0,"k":[0,0],"ix":2},"a":{"a":0,"k":[0,0],"ix":1},"s":{"a":0,"k":[100,100],"ix":3},"r":{"a":0,"k":0,"ix":6},"o":{"a":0,"k":100,"ix":7},"sk":{"a":0,"k":0,"ix":4},"sa":{"a":0,"k":0,"ix":5},"nm":"Transform"}],"nm":"Ellipse 4","np":3,"cix":2,"bm":0,"ix":1,"mn":"ADBE Vector Group","hd":false}],"ip":0,"op":1800,"st":0,"bm":0},{"ddd":0,"ind":2,"ty":4,"nm":"Ellipse 3","sr":1,"ks":{"o":{"a":0,"k":100,"ix":11},"r":{"a":0,"k":40,"ix":10},"p":{"a":0,"k":[270.339,100.846,0],"ix":2},"a":{"a":0,"k":[0,0,0],"ix":1},"s":{"a":0,"k":[100,100,100],"ix":6}},"ao":0,"shapes":[{"ty":"gr","it":[{"d":1,"ty":"el","s":{"a":0,"k":[15.969,15.969],"ix":2},"p":{"a":0,"k":[0,0],"ix":3},"nm":"Ellipse Path 1","mn":"ADBE Vector Shape - Ellipse","hd":false},{"ty":"fl","c":{"a":0,"k":[0.086274509804,0.094117647059,0.117647058824,1],"ix":4},"o":{"a":0,"k":100,"ix":5},"r":1,"bm":0,"nm":"Fill 1","mn":"ADBE Vector Graphic - Fill","hd":false},{"ty":"tr","p":{"a":0,"k":[0,0],"ix":2},"a":{"a":0,"k":[0,0],"ix":1},"s":{"a":0,"k":[100,100],"ix":3},"r":{"a":0,"k":0,"ix":6},"o":{"a":0,"k":100,"ix":7},"sk":{"a":0,"k":0,"ix":4},"sa":{"a":0,"k":0,"ix":5},"nm":"Transform"}],"nm":"Ellipse 3","np":3,"cix":2,"bm":0,"ix":1,"mn":"ADBE Vector Group","hd":false}],"ip":0,"op":1800,"st":0,"bm":0},{"ddd":0,"ind":3,"ty":4,"nm":"Path 280","sr":1,"ks":{"o":{"a":0,"k":100,"ix":11},"r":{"a":0,"k":40,"ix":10},"p":{"a":0,"k":[270.34,100.845,0],"ix":2},"a":{"a":0,"k":[13.202,13.202,0],"ix":1},"s":{"a":0,"k":[100,100,100],"ix":6}},"ao":0,"shapes":[{"ty":"gr","it":[{"ind":0,"ty":"sh","ix":1,"ks":{"a":0,"k":{"i":[[7.291,0],[0,-7.292],[-7.292,0],[0,7.292]],"o":[[-7.292,0],[0,7.291],[7.291,0],[0,-7.291]],"v":[[13.203,0],[0,13.203],[13.203,26.405],[26.405,13.202]],"c":true},"ix":2},"nm":"Path 1","mn":"ADBE Vector Shape - Group","hd":false},{"ty":"fl","c":{"a":0,"k":[1,1,1,1],"ix":4},"o":{"a":0,"k":100,"ix":5},"r":1,"bm":0,"nm":"Fill 1","mn":"ADBE Vector Graphic - Fill","hd":false},{"ty":"tr","p":{"a":0,"k":[0,0],"ix":2},"a":{"a":0,"k":[0,0],"ix":1},"s":{"a":0,"k":[100,100],"ix":3},"r":{"a":0,"k":0,"ix":6},"o":{"a":0,"k":100,"ix":7},"sk":{"a":0,"k":0,"ix":4},"sa":{"a":0,"k":0,"ix":5},"nm":"Transform"}],"nm":"Path 280","np":3,"cix":2,"bm":0,"ix":1,"mn":"ADBE Vector Group","hd":false}],"ip":0,"op":1800,"st":0,"bm":0},{"ddd":0,"ind":4,"ty":4,"nm":"Path 279","sr":1,"ks":{"o":{"a":0,"k":100,"ix":11},"r":{"a":0,"k":114,"ix":10},"p":{"a":0,"k":[268.486,99.291,0],"ix":2},"a":{"a":0,"k":[16.088,16.088,0],"ix":1},"s":{"a":0,"k":[100,100,100],"ix":6}},"ao":0,"shapes":[{"ty":"gr","it":[{"ind":0,"ty":"sh","ix":1,"ks":{"a":0,"k":{"i":[[8.885,0],[0,-8.885],[-8.885,0],[0,8.885],[8.885,0]],"o":[[-8.886,0],[0,8.885],[8.885,0],[0,-8.885],[0,0]],"v":[[16.089,0],[0,16.089],[16.089,32.177],[32.177,16.088],[16.089,0]],"c":true},"ix":2},"nm":"Path 1","mn":"ADBE Vector Shape - Group","hd":false},{"ty":"fl","c":{"a":0,"k":[0.321568627451,0.450980392157,0.635294117647,1],"ix":4},"o":{"a":0,"k":100,"ix":5},"r":1,"bm":0,"nm":"Fill 1","mn":"ADBE Vector Graphic - Fill","hd":false},{"ty":"tr","p":{"a":0,"k":[0,0],"ix":2},"a":{"a":0,"k":[0,0],"ix":1},"s":{"a":0,"k":[100,100],"ix":3},"r":{"a":0,"k":0,"ix":6},"o":{"a":0,"k":100,"ix":7},"sk":{"a":0,"k":0,"ix":4},"sa":{"a":0,"k":0,"ix":5},"nm":"Transform"}],"nm":"Path 279","np":3,"cix":2,"bm":0,"ix":1,"mn":"ADBE Vector Group","hd":false}],"ip":0,"op":1800,"st":0,"bm":0},{"ddd":0,"ind":5,"ty":4,"nm":"Path 273","sr":1,"ks":{"o":{"a":0,"k":100,"ix":11},"r":{"a":0,"k":12,"ix":10},"p":{"a":0,"k":[263.054,114.826,0],"ix":2},"a":{"a":0,"k":[28.827,44.603,0],"ix":1},"s":{"a":0,"k":[100,100,100],"ix":6}},"ao":0,"shapes":[{"ty":"gr","it":[{"ind":0,"ty":"sh","ix":1,"ks":{"a":0,"k":{"i":[[1.557,6.321],[8.054,0.781],[6.433,-2.912],[-6.537,-15.519],[-1.409,4.82],[-4.023,4.92],[2.011,13.626]],"o":[[-1.423,-6.018],[-7.478,-0.491],[-21.119,8.705],[6.537,15.519],[4.772,-16.326],[4.023,-4.921],[-1.361,-9.217]],"v":[[54.381,11.527],[38.456,0.101],[17.052,3.827],[4.481,52.276],[46.719,88.613],[48.731,59.089],[57.279,35.243]],"c":true},"ix":2},"nm":"Path 1","mn":"ADBE Vector Shape - Group","hd":false},{"ty":"fl","c":{"a":0,"k":[1,1,1,1],"ix":4},"o":{"a":0,"k":100,"ix":5},"r":1,"bm":0,"nm":"Fill 1","mn":"ADBE Vector Graphic - Fill","hd":false},{"ty":"tr","p":{"a":0,"k":[0,0],"ix":2},"a":{"a":0,"k":[0,0],"ix":1},"s":{"a":0,"k":[100,100],"ix":3},"r":{"a":0,"k":0,"ix":6},"o":{"a":0,"k":100,"ix":7},"sk":{"a":0,"k":0,"ix":4},"sa":{"a":0,"k":0,"ix":5},"nm":"Transform"}],"nm":"Path 273","np":3,"cix":2,"bm":0,"ix":1,"mn":"ADBE Vector Group","hd":false}],"ip":0,"op":1800,"st":0,"bm":0}]},{"id":"comp_1","layers":[{"ddd":0,"ind":1,"ty":4,"nm":"Path 277","sr":1,"ks":{"o":{"a":0,"k":100,"ix":11},"r":{"a":0,"k":0,"ix":10},"p":{"a":0,"k":[114.086,245.902,0],"ix":2},"a":{"a":0,"k":[28.519,14.152,0],"ix":1},"s":{"a":0,"k":[100,100,100],"ix":6}},"ao":0,"shapes":[{"ty":"gr","it":[{"ind":0,"ty":"sh","ix":1,"ks":{"a":0,"k":{"i":[[6.341,7.549],[15.526,-7.594],[0.393,-6.507],[-5.577,3.063],[-6.969,-3.709],[-0.98,5.283],[0,0],[-1.974,3.277],[0,0]],"o":[[-6.34,-7.552],[0,0],[-0.113,1.862],[6.983,-3.684],[8.315,4.275],[0.98,-5.283],[0,0],[1.974,-3.277],[0,0]],"v":[[55.759,16.951],[12.52,2.098],[0.058,15.269],[5.064,15.287],[27.37,15.327],[43.868,27.041],[38.263,15.526],[51.452,22.983],[42.797,13.18]],"c":true},"ix":2},"nm":"Path 1","mn":"ADBE Vector Shape - Group","hd":false},{"ty":"fl","c":{"a":0,"k":[0.992156862745,0.654901960784,0,1],"ix":4},"o":{"a":0,"k":100,"ix":5},"r":1,"bm":0,"nm":"Fill 1","mn":"ADBE Vector Graphic - Fill","hd":false},{"ty":"tr","p":{"a":0,"k":[0,0],"ix":2},"a":{"a":0,"k":[0,0],"ix":1},"s":{"a":0,"k":[100,100],"ix":3},"r":{"a":0,"k":0,"ix":6},"o":{"a":0,"k":100,"ix":7},"sk":{"a":0,"k":0,"ix":4},"sa":{"a":0,"k":0,"ix":5},"nm":"Transform"}],"nm":"Path 277","np":3,"cix":2,"bm":0,"ix":1,"mn":"ADBE Vector Group","hd":false}],"ip":0,"op":1800,"st":0,"bm":0},{"ddd":0,"ind":2,"ty":4,"nm":"Path 264","sr":1,"ks":{"o":{"a":0,"k":100,"ix":11},"r":{"a":0,"k":0,"ix":10},"p":{"a":0,"k":[129.142,240.916,0],"ix":2},"a":{"a":0,"k":[28.555,13.717,0],"ix":1},"s":{"a":0,"k":[100,100,100],"ix":6}},"ao":0,"shapes":[{"ty":"gr","it":[{"ind":0,"ty":"sh","ix":1,"ks":{"a":0,"k":{"i":[[6.65,7.28],[15.196,-8.234],[0.122,-6.518],[-5.445,3.294],[-7.118,-3.415],[-0.759,5.32],[0,0],[-1.836,3.356],[0,0]],"o":[[-6.65,-7.281],[0,0],[-0.035,1.865],[6.823,-3.972],[8.486,3.924],[0.759,-5.319],[0,0],[1.836,-3.356],[0,0]],"v":[[55.742,15.554],[11.922,2.517],[0.02,16.196],[5.022,16.005],[27.311,15.115],[44.283,26.13],[38.202,14.86],[51.69,21.76],[42.634,12.326]],"c":true},"ix":2},"nm":"Path 1","mn":"ADBE Vector Shape - Group","hd":false},{"ty":"fl","c":{"a":0,"k":[0.929411764706,0.6,0.023529411765,1],"ix":4},"o":{"a":0,"k":100,"ix":5},"r":1,"bm":0,"nm":"Fill 1","mn":"ADBE Vector Graphic - Fill","hd":false},{"ty":"tr","p":{"a":0,"k":[0,0],"ix":2},"a":{"a":0,"k":[0,0],"ix":1},"s":{"a":0,"k":[100,100],"ix":3},"r":{"a":0,"k":0,"ix":6},"o":{"a":0,"k":100,"ix":7},"sk":{"a":0,"k":0,"ix":4},"sa":{"a":0,"k":0,"ix":5},"nm":"Transform"}],"nm":"Path 264","np":3,"cix":2,"bm":0,"ix":1,"mn":"ADBE Vector Group","hd":false}],"ip":0,"op":1800,"st":0,"bm":0}]},{"id":"comp_2","layers":[{"ddd":0,"ind":1,"ty":4,"nm":"Path 276","sr":1,"ks":{"o":{"a":0,"k":100,"ix":11},"r":{"a":0,"k":0,"ix":10},"p":{"a":0,"k":[178.279,166.057,0],"ix":2},"a":{"a":0,"k":[38.567,31.773,0],"ix":1},"s":{"a":0,"k":[100,100,100],"ix":6}},"ao":0,"shapes":[{"ty":"gr","it":[{"ind":0,"ty":"sh","ix":1,"ks":{"a":0,"k":{"i":[[17.224,8.413],[0,0],[-6.008,1.602],[0,0],[-6.409,4.406],[-6.017,6.288],[-6.81,4.406],[0,0],[-3.605,7.21],[-1.469,7.001],[-1.602,8.813]],"o":[[-17.224,-8.412],[0,0],[6.008,-1.602],[0,0],[6.787,-5.449],[0,0],[6.81,-4.406],[0,0],[2.794,-6.586],[0,0],[1.602,-8.813]],"v":[[64.721,2.129],[33.478,12.944],[0.631,61.813],[25.466,42.987],[21.06,63.015],[40.287,45.39],[39.486,60.612],[53.906,42.987],[60.716,56.606],[67.125,36.177],[75.136,41.785]],"c":true},"ix":2},"nm":"Path 1","mn":"ADBE Vector Shape - Group","hd":false},{"ty":"fl","c":{"a":0,"k":[0.156862745098,0.305882352941,0.517647058824,1],"ix":4},"o":{"a":0,"k":100,"ix":5},"r":1,"bm":0,"nm":"Fill 1","mn":"ADBE Vector Graphic - Fill","hd":false},{"ty":"tr","p":{"a":0,"k":[0,0],"ix":2},"a":{"a":0,"k":[0,0],"ix":1},"s":{"a":0,"k":[100,100],"ix":3},"r":{"a":0,"k":0,"ix":6},"o":{"a":0,"k":100,"ix":7},"sk":{"a":0,"k":0,"ix":4},"sa":{"a":0,"k":0,"ix":5},"nm":"Transform"}],"nm":"Path 276","np":3,"cix":2,"bm":0,"ix":1,"mn":"ADBE Vector Group","hd":false}],"ip":0,"op":1800,"st":0,"bm":0},{"ddd":0,"ind":2,"ty":4,"nm":"Path 275","sr":1,"ks":{"o":{"a":0,"k":100,"ix":11},"r":{"a":0,"k":0,"ix":10},"p":{"a":0,"k":[177.1,173.781,0],"ix":2},"a":{"a":0,"k":[53.598,47.189,0],"ix":1},"s":{"a":0,"k":[100,100,100],"ix":6}},"ao":0,"shapes":[{"ty":"gr","it":[{"ind":0,"ty":"sh","ix":1,"ks":{"a":0,"k":{"i":[[15.474,12.117],[0,0],[-5.246,-8.161],[0,0],[-6.995,-1.749],[0,0],[-5.829,-5.246],[0,0],[-4.08,-1.166],[-5.246,15.738]],"o":[[-18.07,-14.572],[0,0],[5.246,8.161],[0,0],[6.995,1.749],[0,0],[5.829,5.246],[0,0],[4.08,1.166],[6.404,-18.581]],"v":[[89.523,5.055],[52.218,12.05],[0.34,83.746],[23.073,75.003],[15.496,94.238],[46.972,75.586],[48.721,93.655],[76.7,73.837],[77.865,88.992],[104.679,56.35]],"c":true},"ix":2},"nm":"Path 1","mn":"ADBE Vector Shape - Group","hd":false},{"ty":"fl","c":{"a":0,"k":[0.321568627451,0.450980392157,0.635294117647,1],"ix":4},"o":{"a":0,"k":100,"ix":5},"r":1,"bm":0,"nm":"Fill 1","mn":"ADBE Vector Graphic - Fill","hd":false},{"ty":"tr","p":{"a":0,"k":[0,0],"ix":2},"a":{"a":0,"k":[0,0],"ix":1},"s":{"a":0,"k":[100,100],"ix":3},"r":{"a":0,"k":0,"ix":6},"o":{"a":0,"k":100,"ix":7},"sk":{"a":0,"k":0,"ix":4},"sa":{"a":0,"k":0,"ix":5},"nm":"Transform"}],"nm":"Path 275","np":3,"cix":2,"bm":0,"ix":1,"mn":"ADBE Vector Group","hd":false}],"ip":0,"op":1800,"st":0,"bm":0},{"ddd":0,"ind":3,"ty":4,"nm":"Path 274","sr":1,"ks":{"o":{"a":0,"k":100,"ix":11},"r":{"a":0,"k":0,"ix":10},"p":{"a":0,"k":[154.655,218.654,0],"ix":2},"a":{"a":0,"k":[60.721,39.495,0],"ix":1},"s":{"a":0,"k":[100,100,100],"ix":6}},"ao":0,"shapes":[{"ty":"gr","it":[{"ind":0,"ty":"sh","ix":1,"ks":{"a":0,"k":{"i":[[28.562,-26.229],[-16.321,-0.582],[-11.124,10.41],[-10.228,0.499],[-11.354,15.448],[-8.953,2.238],[-8.495,12.945],[-9.505,1.728],[-1.165,11.658]],"o":[[0,0],[8.043,0.287],[-11.66,13.108],[15.653,-0.764],[-9.268,14.152],[10.617,-2.654],[-7.19,11.575],[12.824,-2.332],[1.166,-11.657]],"v":[[40.984,16.605],[3.062,72.57],[35.231,52.257],[23.497,78.976],[69.655,40.248],[58.082,71.406],[96.079,28.658],[85.737,60.634],[121.423,11.943]],"c":true},"ix":2},"nm":"Path 1","mn":"ADBE Vector Shape - Group","hd":false},{"ty":"fl","c":{"a":0,"k":[0.674509803922,0.721568627451,0.827450980392,1],"ix":4},"o":{"a":0,"k":100,"ix":5},"r":1,"bm":0,"nm":"Fill 1","mn":"ADBE Vector Graphic - Fill","hd":false},{"ty":"tr","p":{"a":0,"k":[0,0],"ix":2},"a":{"a":0,"k":[0,0],"ix":1},"s":{"a":0,"k":[100,100],"ix":3},"r":{"a":0,"k":0,"ix":6},"o":{"a":0,"k":100,"ix":7},"sk":{"a":0,"k":0,"ix":4},"sa":{"a":0,"k":0,"ix":5},"nm":"Transform"}],"nm":"Path 274","np":3,"cix":2,"bm":0,"ix":1,"mn":"ADBE Vector Group","hd":false}],"ip":0,"op":1800,"st":0,"bm":0}]},{"id":"comp_3","layers":[{"ddd":0,"ind":1,"ty":4,"nm":"Path 272","sr":1,"ks":{"o":{"a":0,"k":100,"ix":11},"r":{"a":0,"k":2,"ix":10},"p":{"a":0,"k":[258.691,135.013,0],"ix":2},"a":{"a":0,"k":[23.918,48.553,0],"ix":1},"s":{"a":0,"k":[100,100,100],"ix":6}},"ao":0,"shapes":[{"ty":"gr","it":[{"ind":0,"ty":"sh","ix":1,"ks":{"a":0,"k":{"i":[[20.057,3.437],[-13.181,-27.508],[-6.304,12.035],[0,0]],"o":[[0,0],[13.181,27.508],[6.304,-12.035],[0,0]],"v":[[5.025,0],[6.171,59.027],[45.713,93.411],[42.275,55.015]],"c":true},"ix":2},"nm":"Path 1","mn":"ADBE Vector Shape - Group","hd":false},{"ty":"fl","c":{"a":0,"k":[0.992156862745,0.654901960784,0,1],"ix":4},"o":{"a":0,"k":100,"ix":5},"r":1,"bm":0,"nm":"Fill 1","mn":"ADBE Vector Graphic - Fill","hd":false},{"ty":"tr","p":{"a":0,"k":[0,0],"ix":2},"a":{"a":0,"k":[0,0],"ix":1},"s":{"a":0,"k":[100,100],"ix":3},"r":{"a":0,"k":0,"ix":6},"o":{"a":0,"k":100,"ix":7},"sk":{"a":0,"k":0,"ix":4},"sa":{"a":0,"k":0,"ix":5},"nm":"Transform"}],"nm":"Path 272","np":3,"cix":2,"bm":0,"ix":1,"mn":"ADBE Vector Group","hd":false}],"ip":0,"op":1800,"st":0,"bm":0},{"ddd":0,"ind":2,"ty":4,"nm":"Path 271","sr":1,"ks":{"o":{"a":0,"k":100,"ix":11},"r":{"a":0,"k":13,"ix":10},"p":{"a":0,"k":[290.317,143.002,0],"ix":2},"a":{"a":0,"k":[16.28,38.598,0],"ix":1},"s":{"a":0,"k":[100,100,100],"ix":6}},"ao":0,"shapes":[{"ty":"gr","it":[{"ind":0,"ty":"sh","ix":1,"ks":{"a":0,"k":{"i":[[9.533,11.61],[-4.779,-13.263],[-4.943,2.664],[4.779,20.405]],"o":[[-16.386,18.875],[4.779,13.263],[5.781,-3.115],[-3.563,-13.359]],"v":[[9.74,0],[6.327,60.706],[27.492,76.521],[29.54,37.75]],"c":true},"ix":2},"nm":"Path 1","mn":"ADBE Vector Shape - Group","hd":false},{"ty":"fl","c":{"a":0,"k":[0.929411764706,0.6,0.023529411765,1],"ix":4},"o":{"a":0,"k":100,"ix":5},"r":1,"bm":0,"nm":"Fill 1","mn":"ADBE Vector Graphic - Fill","hd":false},{"ty":"tr","p":{"a":0,"k":[0,0],"ix":2},"a":{"a":0,"k":[0,0],"ix":1},"s":{"a":0,"k":[100,100],"ix":3},"r":{"a":0,"k":0,"ix":6},"o":{"a":0,"k":100,"ix":7},"sk":{"a":0,"k":0,"ix":4},"sa":{"a":0,"k":0,"ix":5},"nm":"Transform"}],"nm":"Path 271","np":3,"cix":2,"bm":0,"ix":1,"mn":"ADBE Vector Group","hd":false}],"ip":0,"op":1800,"st":0,"bm":0}]},{"id":"comp_4","layers":[{"ddd":0,"ind":1,"ty":4,"nm":"Path 269","sr":1,"ks":{"o":{"a":0,"k":100,"ix":11},"r":{"a":0,"k":0,"ix":10},"p":{"a":0,"k":[226.32,230.144,0],"ix":2},"a":{"a":0,"k":[66.752,58.143,0],"ix":1},"s":{"a":0,"k":[100,100,100],"ix":6}},"ao":0,"shapes":[{"ty":"gr","it":[{"ind":0,"ty":"sh","ix":1,"ks":{"a":0,"k":{"i":[[8.512,-8.741],[-7.791,-1.198],[-4.161,0.763],[-8.99,-1.798],[0,0],[-5.394,-4.795],[1.798,-2.397],[-1.798,-3.596],[2.997,-1.199],[-2.397,-4.795],[-6.847,-1.405],[-0.368,0.031],[0.36,37.441],[8.512,-8.741]],"o":[[0,0],[4.161,0.763],[0,0],[8.99,1.798],[0,0],[5.394,4.795],[-1.798,2.397],[1.798,3.596],[-2.997,1.199],[0.836,1.673],[0.365,-0.03],[106.472,-8.806],[-11.723,3.383],[0,0]],"v":[[102.622,18.5],[84.042,53.861],[96.628,53.861],[69.658,71.841],[85.241,74.838],[51.677,88.623],[61.267,94.017],[24.707,101.209],[31.3,106.004],[0.134,111.398],[12.501,116.285],[13.573,116.2],[133.497,0],[102.622,18.5]],"c":true},"ix":2},"nm":"Path 1","mn":"ADBE Vector Shape - Group","hd":false},{"ty":"fl","c":{"a":0,"k":[0.219607843137,0.254901960784,0.333333333333,1],"ix":4},"o":{"a":0,"k":100,"ix":5},"r":1,"bm":0,"nm":"Fill 1","mn":"ADBE Vector Graphic - Fill","hd":false},{"ty":"tr","p":{"a":0,"k":[0,0],"ix":2},"a":{"a":0,"k":[0,0],"ix":1},"s":{"a":0,"k":[100,100],"ix":3},"r":{"a":0,"k":0,"ix":6},"o":{"a":0,"k":100,"ix":7},"sk":{"a":0,"k":0,"ix":4},"sa":{"a":0,"k":0,"ix":5},"nm":"Transform"}],"nm":"Path 269","np":3,"cix":2,"bm":0,"ix":1,"mn":"ADBE Vector Group","hd":false}],"ip":0,"op":1800,"st":0,"bm":0},{"ddd":0,"ind":2,"ty":4,"nm":"Path 268","sr":1,"ks":{"o":{"a":0,"k":100,"ix":11},"r":{"a":0,"k":0,"ix":10},"p":{"a":0,"k":[201.326,172.204,0],"ix":2},"a":{"a":0,"k":[99.344,118.204,0],"ix":1},"s":{"a":0,"k":[100,100,100],"ix":6}},"ao":0,"shapes":[{"ty":"gr","it":[{"ind":0,"ty":"sh","ix":1,"ks":{"a":0,"k":{"i":[[-3.299,19.799],[34.096,-17.598],[10.862,-36.337],[-146.282,12.099],[3.467,24.158],[-1.965,2.07],[3.992,5.987]],"o":[[3.3,-19.798],[-37.46,19.334],[-19.339,64.694],[128.434,-10.622],[-0.35,-2.833],[12.236,-13.586],[-4.398,-6.6]],"v":[[192.145,19.729],[131.652,9.83],[65.66,142.914],[71.16,234.203],[189.753,99.776],[192.304,92.031],[192.145,58.224]],"c":true},"ix":2},"nm":"Path 1","mn":"ADBE Vector Shape - Group","hd":false},{"ty":"fl","c":{"a":0,"k":[0.086274509804,0.094117647059,0.117647058824,1],"ix":4},"o":{"a":0,"k":100,"ix":5},"r":1,"bm":0,"nm":"Fill 1","mn":"ADBE Vector Graphic - Fill","hd":false},{"ty":"tr","p":{"a":0,"k":[0,0],"ix":2},"a":{"a":0,"k":[0,0],"ix":1},"s":{"a":0,"k":[100,100],"ix":3},"r":{"a":0,"k":0,"ix":6},"o":{"a":0,"k":100,"ix":7},"sk":{"a":0,"k":0,"ix":4},"sa":{"a":0,"k":0,"ix":5},"nm":"Transform"}],"nm":"Path 268","np":3,"cix":2,"bm":0,"ix":1,"mn":"ADBE Vector Group","hd":false}],"ip":0,"op":1800,"st":0,"bm":0}]},{"id":"comp_5","layers":[{"ddd":0,"ind":1,"ty":4,"nm":"Path 278","parent":3,"sr":1,"ks":{"o":{"a":0,"k":100,"ix":11},"r":{"a":0,"k":0,"ix":10},"p":{"a":0,"k":[75.092,14.574,0],"ix":2},"a":{"a":0,"k":[52.802,14.573,0],"ix":1},"s":{"a":0,"k":[100,100,100],"ix":6}},"ao":0,"shapes":[{"ty":"gr","it":[{"ind":0,"ty":"sh","ix":1,"ks":{"a":0,"k":{"i":[[22.184,-2.579],[-7.663,-1.888],[-23.375,-10.541],[-5.786,3.445],[2.923,1.972]],"o":[[0.42,7.881],[16.5,4.125],[14.721,6.639],[-2.544,-2.006],[-33.278,-22.352]],"v":[[0,1.307],[13.609,17.756],[74.566,24.631],[105.604,26.098],[97.404,20.132]],"c":true},"ix":2},"nm":"Path 1","mn":"ADBE Vector Shape - Group","hd":false},{"ty":"fl","c":{"a":0,"k":[0.992156862745,0.752941176471,0,1],"ix":4},"o":{"a":0,"k":100,"ix":5},"r":1,"bm":0,"nm":"Fill 1","mn":"ADBE Vector Graphic - Fill","hd":false},{"ty":"tr","p":{"a":0,"k":[0,0],"ix":2},"a":{"a":0,"k":[0,0],"ix":1},"s":{"a":0,"k":[100,100],"ix":3},"r":{"a":0,"k":0,"ix":6},"o":{"a":0,"k":100,"ix":7},"sk":{"a":0,"k":0,"ix":4},"sa":{"a":0,"k":0,"ix":5},"nm":"Transform"}],"nm":"Path 278","np":3,"cix":2,"bm":0,"ix":1,"mn":"ADBE Vector Group","hd":false}],"ip":0,"op":1800,"st":0,"bm":0},{"ddd":0,"ind":2,"ty":4,"nm":"Path 270","parent":3,"sr":1,"ks":{"o":{"a":0,"k":100,"ix":11},"r":{"a":0,"k":0,"ix":10},"p":{"a":0,"k":[145.196,61.764,0],"ix":2},"a":{"a":0,"k":[16.198,28.607,0],"ix":1},"s":{"a":0,"k":[100,100,100],"ix":6}},"ao":0,"shapes":[{"ty":"gr","it":[{"ind":0,"ty":"sh","ix":1,"ks":{"a":0,"k":{"i":[[29.894,28.452],[-5.163,-8.918],[-4.966,-21.284]],"o":[[-4.453,2.282],[7.804,13.48],[1.845,0.002]],"v":[[7.035,0],[2.049,16.064],[31.137,57.214]],"c":true},"ix":2},"nm":"Path 1","mn":"ADBE Vector Shape - Group","hd":false},{"ty":"fl","c":{"a":0,"k":[0.086274509804,0.094117647059,0.117647058824,1],"ix":4},"o":{"a":0,"k":100,"ix":5},"r":1,"bm":0,"nm":"Fill 1","mn":"ADBE Vector Graphic - Fill","hd":false},{"ty":"tr","p":{"a":0,"k":[0,0],"ix":2},"a":{"a":0,"k":[0,0],"ix":1},"s":{"a":0,"k":[100,100],"ix":3},"r":{"a":0,"k":0,"ix":6},"o":{"a":0,"k":100,"ix":7},"sk":{"a":0,"k":0,"ix":4},"sa":{"a":0,"k":0,"ix":5},"nm":"Transform"}],"nm":"Path 270","np":3,"cix":2,"bm":0,"ix":1,"mn":"ADBE Vector Group","hd":false}],"ip":0,"op":1800,"st":0,"bm":0},{"ddd":0,"ind":3,"ty":4,"nm":"Path 267","sr":1,"ks":{"o":{"a":0,"k":100,"ix":11},"r":{"a":1,"k":[{"i":{"x":[0.833],"y":[0.833]},"o":{"x":[0.167],"y":[0.167]},"t":96,"s":[30]},{"i":{"x":[0.833],"y":[0.833]},"o":{"x":[0.167],"y":[0.167]},"t":179,"s":[-4]},{"t":260,"s":[30]}],"ix":10},"p":{"a":0,"k":[265.037,96.473,0],"ix":2},"a":{"a":0,"k":[2.309,45.411,0],"ix":1},"s":{"a":0,"k":[100,100,100],"ix":6}},"ao":0,"shapes":[{"ty":"gr","it":[{"ind":0,"ty":"sh","ix":1,"ks":{"a":0,"k":{"i":[[47.535,31.929],[0,0],[-3.547,0],[-58.195,-12.15],[-2.128,0]],"o":[[-47.535,-31.927],[-4.257,3.548],[3.547,0],[47.552,9.928],[2.128,0]],"v":[[119.693,20.133],[6.886,3.815],[1.21,44.965],[93.443,44.255],[160.134,90.371]],"c":true},"ix":2},"nm":"Path 1","mn":"ADBE Vector Shape - Group","hd":false},{"ty":"fl","c":{"a":0,"k":[0.992156862745,0.654901960784,0,1],"ix":4},"o":{"a":0,"k":100,"ix":5},"r":1,"bm":0,"nm":"Fill 1","mn":"ADBE Vector Graphic - Fill","hd":false},{"ty":"tr","p":{"a":0,"k":[0,0],"ix":2},"a":{"a":0,"k":[0,0],"ix":1},"s":{"a":0,"k":[100,100],"ix":3},"r":{"a":0,"k":0,"ix":6},"o":{"a":0,"k":100,"ix":7},"sk":{"a":0,"k":0,"ix":4},"sa":{"a":0,"k":0,"ix":5},"nm":"Transform"}],"nm":"Path 267","np":3,"cix":2,"bm":0,"ix":1,"mn":"ADBE Vector Group","hd":false}],"ip":0,"op":1800,"st":0,"bm":0},{"ddd":0,"ind":4,"ty":4,"nm":"Path 266","sr":1,"ks":{"o":{"a":0,"k":100,"ix":11},"r":{"a":0,"k":24,"ix":10},"p":{"a":0,"k":[322.17,144.375,0],"ix":2},"a":{"a":0,"k":[72.398,29.368,0],"ix":1},"s":{"a":0,"k":[100,100,100],"ix":6}},"ao":0,"shapes":[{"ty":"gr","it":[{"ind":0,"ty":"sh","ix":1,"ks":{"a":0,"k":{"i":[[43.987,12.059],[0,-5.676],[0,0],[-26.632,-8.524],[1.419,6.386]],"o":[[-43.988,-12.061],[0,5.676],[25.389,-11.718],[31.719,9.912],[-1.419,-6.385]],"v":[[86.556,5.909],[0,8.747],[10.642,34.288],[91.523,29.322],[144.734,57.701]],"c":true},"ix":2},"nm":"Path 1","mn":"ADBE Vector Shape - Group","hd":false},{"ty":"fl","c":{"a":0,"k":[0.898039215686,0.580392156863,0.019607843137,1],"ix":4},"o":{"a":0,"k":100,"ix":5},"r":1,"bm":0,"nm":"Fill 1","mn":"ADBE Vector Graphic - Fill","hd":false},{"ty":"tr","p":{"a":0,"k":[0,0],"ix":2},"a":{"a":0,"k":[0,0],"ix":1},"s":{"a":0,"k":[100,100],"ix":3},"r":{"a":0,"k":0,"ix":6},"o":{"a":0,"k":100,"ix":7},"sk":{"a":0,"k":0,"ix":4},"sa":{"a":0,"k":0,"ix":5},"nm":"Transform"}],"nm":"Path 266","np":3,"cix":2,"bm":0,"ix":1,"mn":"ADBE Vector Group","hd":false}],"ip":0,"op":1800,"st":0,"bm":0}]},{"id":"comp_6","layers":[{"ddd":0,"ind":1,"ty":4,"nm":"Path 262","sr":1,"ks":{"o":{"a":0,"k":100,"ix":11},"r":{"a":0,"k":0,"ix":10},"p":{"a":0,"k":[116.239,322.586,0],"ix":2},"a":{"a":0,"k":[7.262,10.936,0],"ix":1},"s":{"a":0,"k":[100,100,100],"ix":6}},"ao":0,"shapes":[{"ty":"gr","it":[{"ind":0,"ty":"sh","ix":1,"ks":{"a":0,"k":{"i":[[0.628,6.282],[3.813,1.205],[-11.805,4.19]],"o":[[-0.705,-3.937],[-11.436,6.238],[3.981,-2.787]],"v":[[13.913,8.362],[6.564,0],[11.611,21.28]],"c":true},"ix":2},"nm":"Path 1","mn":"ADBE Vector Shape - Group","hd":false},{"ty":"fl","c":{"a":0,"k":[0.745098039216,0.36862745098,0.105882352941,1],"ix":4},"o":{"a":0,"k":100,"ix":5},"r":1,"bm":0,"nm":"Fill 1","mn":"ADBE Vector Graphic - Fill","hd":false},{"ty":"tr","p":{"a":0,"k":[0,0],"ix":2},"a":{"a":0,"k":[0,0],"ix":1},"s":{"a":0,"k":[100,100],"ix":3},"r":{"a":0,"k":0,"ix":6},"o":{"a":0,"k":100,"ix":7},"sk":{"a":0,"k":0,"ix":4},"sa":{"a":0,"k":0,"ix":5},"nm":"Transform"}],"nm":"Path 262","np":3,"cix":2,"bm":0,"ix":1,"mn":"ADBE Vector Group","hd":false}],"ip":0,"op":1800,"st":0,"bm":0},{"ddd":0,"ind":2,"ty":4,"nm":"Path 261","sr":1,"ks":{"o":{"a":0,"k":50,"ix":11},"r":{"a":0,"k":0,"ix":10},"p":{"a":0,"k":[209.477,309.623,0],"ix":2},"a":{"a":0,"k":[100.475,23.898,0],"ix":1},"s":{"a":0,"k":[100,100,100],"ix":6}},"ao":0,"shapes":[{"ty":"gr","it":[{"ind":0,"ty":"sh","ix":1,"ks":{"a":0,"k":{"i":[[-7.53,2.67],[-8.837,4.912],[4.8,2.446],[54.123,-6.697],[25.931,6.175]],"o":[[24.28,-7.31],[-1.877,-5.05],[-3.992,5.167],[-61.671,10.438],[-0.603,6.936]],"v":[[11.586,47.206],[200.95,11.657],[190.568,0],[117.318,20.466],[0.053,36.084]],"c":true},"ix":2},"nm":"Path 1","mn":"ADBE Vector Shape - Group","hd":false},{"ty":"fl","c":{"a":0,"k":[0.282352941176,0.129411764706,0.011764705882,1],"ix":4},"o":{"a":0,"k":100,"ix":5},"r":1,"bm":0,"nm":"Fill 1","mn":"ADBE Vector Graphic - Fill","hd":false},{"ty":"tr","p":{"a":0,"k":[0,0],"ix":2},"a":{"a":0,"k":[0,0],"ix":1},"s":{"a":0,"k":[100,100],"ix":3},"r":{"a":0,"k":0,"ix":6},"o":{"a":0,"k":100,"ix":7},"sk":{"a":0,"k":0,"ix":4},"sa":{"a":0,"k":0,"ix":5},"nm":"Transform"}],"nm":"Path 261","np":3,"cix":2,"bm":0,"ix":1,"mn":"ADBE Vector Group","hd":false}],"ip":0,"op":1800,"st":0,"bm":0},{"ddd":0,"ind":3,"ty":4,"nm":"Path 256","sr":1,"ks":{"o":{"a":0,"k":100,"ix":11},"r":{"a":0,"k":0,"ix":10},"p":{"a":0,"k":[209.464,308.228,0],"ix":2},"a":{"a":0,"k":[100.487,25.293,0],"ix":1},"s":{"a":0,"k":[100,100,100],"ix":6}},"ao":0,"shapes":[{"ty":"gr","it":[{"ind":0,"ty":"sh","ix":1,"ks":{"a":0,"k":{"i":[[-11.436,6.238],[-104.283,14.72],[0,0],[-2.599,-9.59],[24.28,-7.309]],"o":[[0,0],[29.949,-3.284],[0,0],[-8.837,4.912],[-11.805,4.192]],"v":[[6.564,28.715],[132.559,6.008],[184.86,0],[200.974,14.446],[11.611,49.995]],"c":true},"ix":2},"nm":"Path 1","mn":"ADBE Vector Shape - Group","hd":false},{"ty":"fl","c":{"a":0,"k":[0.376470588235,0.192156862745,0.054901960784,1],"ix":4},"o":{"a":0,"k":100,"ix":5},"r":1,"bm":0,"nm":"Fill 1","mn":"ADBE Vector Graphic - Fill","hd":false},{"ty":"tr","p":{"a":0,"k":[0,0],"ix":2},"a":{"a":0,"k":[0,0],"ix":1},"s":{"a":0,"k":[100,100],"ix":3},"r":{"a":0,"k":0,"ix":6},"o":{"a":0,"k":100,"ix":7},"sk":{"a":0,"k":0,"ix":4},"sa":{"a":0,"k":0,"ix":5},"nm":"Transform"}],"nm":"Path 256","np":3,"cix":2,"bm":0,"ix":1,"mn":"ADBE Vector Group","hd":false}],"ip":0,"op":1800,"st":0,"bm":0}]},{"id":"comp_7","layers":[{"ddd":0,"ind":1,"ty":4,"nm":"Path 255","sr":1,"ks":{"o":{"a":0,"k":100,"ix":11},"r":{"a":0,"k":0,"ix":10},"p":{"a":0,"k":[130.327,338.007,0],"ix":2},"a":{"a":0,"k":[43.254,58.495,0],"ix":1},"s":{"a":0,"k":[100,100,100],"ix":6}},"ao":0,"shapes":[{"ty":"gr","it":[{"ind":0,"ty":"sh","ix":1,"ks":{"a":0,"k":{"i":[[0,0],[0,0],[-7.984,12.898],[-2.457,-7.37],[-6.142,19.654],[0,0],[2.457,19.04]],"o":[[0,0],[0,0],[7.984,-12.898],[2.456,7.37],[6.142,-19.654],[0,0],[-2.456,-19.037]],"v":[[64.838,0],[37.201,0.614],[0.964,116.08],[45.185,36.851],[48.87,112.394],[64.224,38.079],[86.335,96.426]],"c":true},"ix":2},"nm":"Path 1","mn":"ADBE Vector Shape - Group","hd":false},{"ty":"fl","c":{"a":0,"k":[0.086274509804,0.094117647059,0.117647058824,1],"ix":4},"o":{"a":0,"k":100,"ix":5},"r":1,"bm":0,"nm":"Fill 1","mn":"ADBE Vector Graphic - Fill","hd":false},{"ty":"tr","p":{"a":0,"k":[0,0],"ix":2},"a":{"a":0,"k":[0,0],"ix":1},"s":{"a":0,"k":[100,100],"ix":3},"r":{"a":0,"k":0,"ix":6},"o":{"a":0,"k":100,"ix":7},"sk":{"a":0,"k":0,"ix":4},"sa":{"a":0,"k":0,"ix":5},"nm":"Transform"}],"nm":"Path 255","np":3,"cix":2,"bm":0,"ix":1,"mn":"ADBE Vector Group","hd":false}],"ip":0,"op":1800,"st":0,"bm":0},{"ddd":0,"ind":2,"ty":4,"nm":"Path 254","sr":1,"ks":{"o":{"a":0,"k":100,"ix":11},"r":{"a":0,"k":0,"ix":10},"p":{"a":0,"k":[130.743,354.695,0],"ix":2},"a":{"a":0,"k":[56.743,91.236,0],"ix":1},"s":{"a":0,"k":[100,100,100],"ix":6}},"ao":0,"shapes":[{"ty":"gr","it":[{"ind":0,"ty":"sh","ix":1,"ks":{"a":0,"k":{"i":[[9.308,3.1],[8.066,-19.856],[-22.959,-3.102],[-2.361,8.228],[0,0],[0.113,-0.393],[-24.922,-6.527],[0,0],[-12.41,24.82]],"o":[[-9.308,-3.102],[0,0],[21.914,2.961],[0.111,-0.391],[0,0],[-2.434,8.549],[26.061,6.826],[0,0],[12.41,-24.82]],"v":[[75.676,5.937],[46.513,11.521],[4.939,164.785],[55.63,69.271],[55.82,68.608],[55.63,69.271],[50.856,182.159],[77.537,81.638],[111.044,174.092]],"c":true},"ix":2},"nm":"Path 1","mn":"ADBE Vector Shape - Group","hd":false},{"ty":"fl","c":{"a":0,"k":[0.274509803922,0.294117647059,0.333333333333,1],"ix":4},"o":{"a":0,"k":100,"ix":5},"r":1,"bm":0,"nm":"Fill 1","mn":"ADBE Vector Graphic - Fill","hd":false},{"ty":"tr","p":{"a":0,"k":[0,0],"ix":2},"a":{"a":0,"k":[0,0],"ix":1},"s":{"a":0,"k":[100,100],"ix":3},"r":{"a":0,"k":0,"ix":6},"o":{"a":0,"k":100,"ix":7},"sk":{"a":0,"k":0,"ix":4},"sa":{"a":0,"k":0,"ix":5},"nm":"Transform"}],"nm":"Path 254","np":3,"cix":2,"bm":0,"ix":1,"mn":"ADBE Vector Group","hd":false}],"ip":0,"op":1800,"st":0,"bm":0}]}],"layers":[{"ddd":0,"ind":1,"ty":0,"nm":"Eyes","refId":"comp_0","sr":1,"ks":{"o":{"a":0,"k":100,"ix":11},"r":{"a":0,"k":0,"ix":10},"p":{"a":1,"k":[{"i":{"x":0.833,"y":0.833},"o":{"x":0.167,"y":0.167},"t":96,"s":[250,250,0],"to":[1.667,-1.167,0],"ti":[0,0,0]},{"i":{"x":0.833,"y":0.833},"o":{"x":0.167,"y":0.167},"t":177,"s":[260,243,0],"to":[0,0,0],"ti":[1.667,-1.167,0]},{"t":336,"s":[250,250,0]}],"ix":2},"a":{"a":0,"k":[250,250,0],"ix":1},"s":{"a":0,"k":[100,100,100],"ix":6}},"ao":0,"w":500,"h":500,"ip":0,"op":1800,"st":0,"bm":0},{"ddd":0,"ind":2,"ty":0,"nm":"Legs","refId":"comp_1","sr":1,"ks":{"o":{"a":0,"k":100,"ix":11},"r":{"a":0,"k":0,"ix":10},"p":{"a":0,"k":[250,250,0],"ix":2},"a":{"a":0,"k":[176,196,0],"ix":1},"s":{"a":0,"k":[100,100,100],"ix":6}},"ao":0,"w":352,"h":392,"ip":0,"op":1800,"st":0,"bm":0},{"ddd":0,"ind":3,"ty":0,"nm":"Wings","refId":"comp_2","sr":1,"ks":{"o":{"a":0,"k":100,"ix":11},"r":{"a":1,"k":[{"i":{"x":[0.833],"y":[0.833]},"o":{"x":[0.167],"y":[0.167]},"t":94,"s":[0]},{"i":{"x":[0.833],"y":[0.833]},"o":{"x":[0.167],"y":[0.167]},"t":177,"s":[7]},{"t":336,"s":[0]}],"ix":10},"p":{"a":0,"k":[250,250,0],"ix":2},"a":{"a":0,"k":[250,250,0],"ix":1},"s":{"a":0,"k":[100,100,100],"ix":6}},"ao":0,"w":500,"h":500,"ip":0,"op":1800,"st":0,"bm":0},{"ddd":0,"ind":4,"ty":0,"nm":"Chin","refId":"comp_3","sr":1,"ks":{"o":{"a":0,"k":100,"ix":11},"r":{"a":0,"k":0,"ix":10},"p":{"a":1,"k":[{"i":{"x":0.833,"y":0.833},"o":{"x":0.167,"y":0.167},"t":96,"s":[250,250,0],"to":[1.667,-1.167,0],"ti":[0,0,0]},{"i":{"x":0.833,"y":0.833},"o":{"x":0.167,"y":0.167},"t":177,"s":[260,243,0],"to":[0,0,0],"ti":[1.667,-1.167,0]},{"t":336,"s":[250,250,0]}],"ix":2},"a":{"a":0,"k":[250,250,0],"ix":1},"s":{"a":0,"k":[100,100,100],"ix":6}},"ao":0,"w":500,"h":500,"ip":0,"op":1800,"st":0,"bm":0},{"ddd":0,"ind":5,"ty":0,"nm":"Body","refId":"comp_4","sr":1,"ks":{"o":{"a":0,"k":100,"ix":11},"r":{"a":1,"k":[{"i":{"x":[0.833],"y":[0.833]},"o":{"x":[0.167],"y":[0.167]},"t":94,"s":[0]},{"i":{"x":[0.833],"y":[0.833]},"o":{"x":[0.167],"y":[0.167]},"t":177,"s":[7]},{"t":354,"s":[0]}],"ix":10},"p":{"a":0,"k":[250,250,0],"ix":2},"a":{"a":0,"k":[250,250,0],"ix":1},"s":{"a":0,"k":[100,100,100],"ix":6}},"ao":0,"w":500,"h":500,"ip":0,"op":1800,"st":0,"bm":0},{"ddd":0,"ind":6,"ty":0,"nm":"Peek","refId":"comp_5","sr":1,"ks":{"o":{"a":0,"k":100,"ix":11},"r":{"a":0,"k":0,"ix":10},"p":{"a":0,"k":[250,250,0],"ix":2},"a":{"a":0,"k":[250,250,0],"ix":1},"s":{"a":0,"k":[100,100,100],"ix":6}},"ao":0,"w":500,"h":500,"ip":0,"op":1800,"st":0,"bm":0},{"ddd":0,"ind":7,"ty":0,"nm":"Wood","refId":"comp_6","sr":1,"ks":{"o":{"a":0,"k":100,"ix":11},"r":{"a":0,"k":0,"ix":10},"p":{"a":0,"k":[250,250,0],"ix":2},"a":{"a":0,"k":[250,250,0],"ix":1},"s":{"a":0,"k":[100,100,100],"ix":6}},"ao":0,"w":500,"h":500,"ip":0,"op":1800,"st":0,"bm":0},{"ddd":0,"ind":8,"ty":0,"nm":"Tail","refId":"comp_7","sr":1,"ks":{"o":{"a":0,"k":100,"ix":11},"r":{"a":1,"k":[{"i":{"x":[0.833],"y":[0.833]},"o":{"x":[0.167],"y":[0.167]},"t":94,"s":[0]},{"i":{"x":[0.833],"y":[0.833]},"o":{"x":[0.167],"y":[0.167]},"t":177,"s":[12]},{"t":255,"s":[0]}],"ix":10},"p":{"a":0,"k":[250,250,0],"ix":2},"a":{"a":0,"k":[250,250,0],"ix":1},"s":{"a":0,"k":[100,100,100],"ix":6}},"ao":0,"w":500,"h":500,"ip":0,"op":1800,"st":0,"bm":0}],"markers":[]}